end_of_file_fixer/__init__.py
end_of_file_fixer/main.py
end_of_file_fixer/py.typed
end_of_file_fixer-0.2.2.dist-info/WHEEL
end_of_file_fixer-0.2.2.dist-info/entry_points.txt
end_of_file_fixer-0.2.2.dist-info/METADATA
end_of_file_fixer-0.2.2.dist-info/RECORD
