Metadata-Version: 2.3
Name: end-of-file-fixer
Version: 0.2.2
Summary: A command-line tool that ensures all your text files end with exactly one newline character
Keywords: python
Author: community-of-python
Classifier: Typing :: Typed
Classifier: Programming Language :: Python :: 3.10
Classifier: Programming Language :: Python :: 3.11
Classifier: Programming Language :: Python :: 3.12
Classifier: Programming Language :: Python :: 3.13
Classifier: Programming Language :: Python :: 3.14
Requires-Dist: pathspec
Requires-Python: >=3.10, <4
Project-URL: Changelogs, https://github.com/community-of-python/end-of-file-fixer/releases
Project-URL: Issues, https://github.com/community-of-python/end-of-file-fixer/issues
Project-URL: Repository, https://github.com/community-of-python/end-of-file-fixer
